{
  "version": "7",
  "dialect": "postgresql",
  "entries": [
    {
      "idx": 0,
      "version": "7",
      "when": 1783617594751,
      "tag": "0000_living_blur",
      "breakpoints": true
    },
    {
      "idx": 1,
      "version": "7",
      "when": 1783630898523,
      "tag": "0001_lying_gorgon",
      "breakpoints": true
    },
    {
      "idx": 2,
      "version": "7",
      "when": 1783853014917,
      "tag": "0002_large_elektra",
      "breakpoints": true
    },
    {
      "idx": 3,
      "version": "7",
      "when": 1783883225392,
      "tag": "0003_absurd_lethal_legion",
      "breakpoints": true
    },
    {
      "idx": 4,
      "version": "7",
      "when": 1784054460475,
      "tag": "0004_black_thunderball",
      "breakpoints": true
    },
    {
      "idx": 5,
      "version": "7",
      "when": 1784317441541,
      "tag": "0005_mighty_network",
      "breakpoints": true
    },
    {
      "idx": 6,
      "version": "7",
      "when": 1784397635142,
      "tag": "0006_small_dexter_bennett",
      "breakpoints": true
    }
  ]
}